README.md
setup.py
helium/__init__.py
helium/_impl/__init__.py
helium/_impl/match_type.py
helium/_impl/selenium_wrappers.py
helium/_impl/util/__init__.py
helium/_impl/util/dictionary.py
helium/_impl/util/geom.py
helium/_impl/util/html.py
helium/_impl/util/inspect_.py
helium/_impl/util/lang.py
helium/_impl/util/os_.py
helium/_impl/util/path.py
helium/_impl/util/system.py
helium/_impl/util/xpath.py
helium/_impl/webdrivers/linux/chromedriver
helium/_impl/webdrivers/linux/geckodriver
helium/_impl/webdrivers/mac/chromedriver
helium/_impl/webdrivers/mac/geckodriver
helium/_impl/webdrivers/windows/chromedriver.exe
helium/_impl/webdrivers/windows/geckodriver.exe
helium_h5.egg-info/PKG-INFO
helium_h5.egg-info/SOURCES.txt
helium_h5.egg-info/dependency_links.txt
helium_h5.egg-info/not-zip-safe
helium_h5.egg-info/requires.txt
helium_h5.egg-info/top_level.txt