Metadata-Version: 1.2
Name: helium-h5
Version: 0.0.1
Summary: Lighter browser automation based on Selenium and Helium.
Home-page: https://gitee.com/remoo/selenium-h5
Author: HelloYang
Author-email: remoo@126.com
License: UNKNOWN
Keywords: helium selenium browser automation h5
Platform: UNKNOWN
Classifier: Development Status :: 5 - Production/Stable
Classifier: Intended Audience :: Developers
Classifier: License :: OSI Approved :: MIT License
Classifier: Topic :: Software Development :: Testing
Classifier: Topic :: Software Development :: Libraries
Classifier: Programming Language :: Python
Classifier: Programming Language :: Python :: 3.5
Classifier: Programming Language :: Python :: 3.6
Classifier: Programming Language :: Python :: 3.7
Classifier: Programming Language :: Python :: 3.8
Classifier: Operating System :: Microsoft :: Windows
Classifier: Operating System :: POSIX :: Linux
Classifier: Operating System :: MacOS :: MacOS X
Requires-Python: >=3
